hello_pypi/cli.py
zoomai-1.0.1.dist-info/METADATA
zoomai-1.0.1.dist-info/WHEEL
zoomai-1.0.1.dist-info/entry_points.txt
zoomai-1.0.1.dist-info/top_level.txt
zoomai-1.0.1.dist-info/RECORD
